retracto/.env
retracto/__init__.py
retracto/app.py
retracto/client_secret.json
retracto/helpers.py
retracto-1.0.4.dist-info/entry_points.txt
retracto-1.0.4.dist-info/LICENSE
retracto-1.0.4.dist-info/WHEEL
retracto-1.0.4.dist-info/METADATA
retracto-1.0.4.dist-info/RECORD
