Metadata-Version: 2.1
Name: retracto
Version: 1.0.4
Summary: This app helps you as a youtube contnt creator to delete abusive and spam comments on a video in one shot.
Author: Amit Krishna A
Author-email: amit.ananthkumar@gmail.com
Requires-Python: >=3.7,<4.0
Classifier: Programming Language :: Python :: 3
Classifier: Programming Language :: Python :: 3.7
Classifier: Programming Language :: Python :: 3.8
Classifier: Programming Language :: Python :: 3.9
Classifier: Programming Language :: Python :: 3.10
Requires-Dist: cohere (>=2.4.2,<3.0.0)
Requires-Dist: google-api-python-client (>=2.62.0,<3.0.0)
Requires-Dist: google-auth-oauthlib (>=0.5.3,<0.6.0)
Requires-Dist: python-dotenv (>=0.21.0,<0.22.0)
Requires-Dist: requests (>=2.28.1,<3.0.0)
Requires-Dist: typer[all] (>=0.6.1,<0.7.0)
